{"cameraMode":{"drawMode":0,"name":"Shaded","section":"Shading Mode"},"sceneLighting":true,"audioPlay":false,"sceneViewState":{"m_AlwaysRefresh":false,"showFog":true,"showSkybox":true,"showFlares":true,"showImageEffects":true,"showParticleSystems":true,"showVisualEffectGraphs":true,"m_FxEnabled":true},"in2DMode":false,"pivot":{"x":-11.5032958984375,"y":0.9199648499488831,"z":-2.5307111740112306},"rotation":{"x":0.006297875661402941,"y":0.9903003573417664,"z":-0.13028475642204286,"w":0.04786960035562515},"size":1.1829546689987183,"orthographic":false}